<?xml version="1.0" encoding="utf-8"?>
<odoo>
    <record id="account_fiscal_position_uae_countries" model="account.fiscal.position.template">
        <field name="name">UAE</field>
        <field name="auto_apply" eval="True"/>
        <field name="sequence" eval="1"/>
        <field name="country_id" ref="base.ae"/>
        <field name="chart_template_id" ref="uae_chart_template_standard"/>
    </record>

    <record id="account_fiscal_position_non_uae_countries" model="account.fiscal.position.template">
        <field name="name">Non-UAE</field>
        <field name="auto_apply" eval="True"/>
        <field name="chart_template_id" ref="uae_chart_template_standard"/>
    </record>
    <record id="acccount_fiscal_position_tax_non_uae_01" model="account.fiscal.position.tax.template">
        <field name="tax_src_id" ref="uae_sale_tax_5"/>
        <field name="tax_dest_id" ref="uae_sale_tax_0"/>
        <field name="position_id" ref="account_fiscal_position_non_uae_countries"/>
    </record>
    <record id="acccount_fiscal_position_tax_non_uae_02" model="account.fiscal.position.tax.template">
        <field name="tax_src_id" ref="uae_purchase_tax_5"/>
        <field name="tax_dest_id" ref="uae_purchase_tax_0"/>
        <field name="position_id" ref="account_fiscal_position_non_uae_countries"/>
    </record>
</odoo>
